pyterrier_anserini/__init__.py
pyterrier_anserini/_index.py
pyterrier_anserini/_indexer.py
pyterrier_anserini/_java.py
pyterrier_anserini/_legacy.py
pyterrier_anserini/_reranker.py
pyterrier_anserini/_retriever.py
pyterrier_anserini/_similarity.py
pyterrier_anserini/_text_loader.py
pyterrier_anserini/_util.py
pyterrier_anserini/pt_docs/api.rst
pyterrier_anserini/pt_docs/extras.rst
pyterrier_anserini/pt_docs/index.rst
pyterrier_anserini-0.1.4.dist-info/licenses/LICENSE.txt
pyterrier_anserini-0.1.4.dist-info/METADATA
pyterrier_anserini-0.1.4.dist-info/WHEEL
pyterrier_anserini-0.1.4.dist-info/entry_points.txt
pyterrier_anserini-0.1.4.dist-info/top_level.txt
pyterrier_anserini-0.1.4.dist-info/RECORD
