Metadata-Version: 2.4
Name: pyterrier-anserini
Version: 0.1.4
Summary: Anserini + PyTerrier
Author-email: Sean MacAvaney <sean.macavaney@glasgow.ac.uk>, Craig Macdonald <craigm@dcs.gla.ac.uk>
Maintainer-email: Sean MacAvaney <sean.macavaney@glasgow.ac.uk>, Craig Macdonald <craigm@dcs.gla.ac.uk>
Project-URL: Repository, https://github.com/seanmacavaney/pyterrier-anserini
Project-URL: Bug Tracker, https://github.com/seanmacavaney/pyterrier-anserini/issues
Classifier: Programming Language :: Python
Classifier: Operating System :: OS Independent
Classifier: Topic :: Text Processing
Classifier: Topic :: Text Processing :: Indexing
Classifier: License :: OSI Approved :: Mozilla Public License 2.0 (MPL 2.0)
Requires-Python: >=3.9
License-File: LICENSE.txt
Requires-Dist: python-terrier>=0.11.0
Requires-Dist: pyserini>=0.36.0
Requires-Dist: pyterrier-alpha>=0.4.3
Dynamic: license-file
